Metadata-Version: 2.1
Name: smallab
Version: 2.3.1
Summary: smallab (Small Lab) is an experiment framework designed to be easy to use with your experiment
Home-page: https://github.com/octopuscabbage/smallab
License: BSD 2-Clause License
License-File: LICENSE
Requires-Dist: joblib
Requires-Dist: numpy
Requires-Dist: tqdm
Requires-Dist: humanhash3
Requires-Dist: python-dateutil
Requires-Dist: dill
Requires-Dist: scikit-learn
